api_hunter_cli/__init__.py
api_hunter_cli/main.py
api_hunter_cli/playwright_custom.py
api_hunter_cli/post_install.py
api_hunter_cli-0.2.1.dist-info/LICENSE
api_hunter_cli-0.2.1.dist-info/METADATA
api_hunter_cli-0.2.1.dist-info/WHEEL
api_hunter_cli-0.2.1.dist-info/entry_points.txt
api_hunter_cli-0.2.1.dist-info/top_level.txt
api_hunter_cli-0.2.1.dist-info/RECORD
