Metadata-Version: 2.1
Name: api-hunter-cli
Version: 0.2.1
Summary: CLI tool for finding hidden apis in a certain url.
Home-page: https://github.com/engcarlosperezmolero/api_hunter_cli
Author: Charly Molero
Author-email: perez.moleroc@gmail.com
Classifier: Development Status :: 3 - Alpha
Classifier: Intended Audience :: Developers
Classifier: License :: OSI Approved :: MIT License
Classifier: Operating System :: OS Independent
Classifier: Programming Language :: Python
Classifier: Programming Language :: Python :: 3
Classifier: Programming Language :: Python :: 3.7
Classifier: Programming Language :: Python :: 3.8
Classifier: Programming Language :: Python :: 3.9
Classifier: Programming Language :: Python :: 3.10
Requires-Python: >=3.7
License-File: LICENSE
Requires-Dist: playwright
Requires-Dist: typer[all]
Requires-Dist: yaspin
Requires-Dist: inquirer
